{"src/configuration":[],"src/extension":["Не удалось открыть файл makefile.","Не удалось открыть файл журнала сборки.","Расширение {0} деактивировано."],"src/launch":["Нет","Да","Ошибка сборки. Все равно продолжить?","Невозможно {0}, так как не задана конфигурация запуска, а список целей запуска пуст. Дважды проверьте конфигурацию файла makefile и целевой объект сборки.","Невозможно {0}, так как не задана конфигурация запуска. Выберите один из вариантов быстрого выбора.","Невозможно {0}, пока не будет выбрана активная конфигурация запуска."],"src/make":["(рекурсивно)","Проект настраивается в фоновом режиме и {0} может работать на устаревших входных данных.","Не {0}, так как проект уже выполняет '{1}'.","Да","Нет","Выполняется сборка ${0} текущей конфигурации файла makefile ${0}","Отмена...","Создание выходных данных пробного запуска","(специально для целевых объектов)","Отмена...","Предварительная настройка ${0}","Отмена предварительной настройки","Последующая настройка: ${0}","Отмена после настройки","Да (больше не показывать)","Нет","Выполняется настройка проекта. Код все еще может выполняться в режиме --dry-run. Вы хотите продолжить?","Настройка","Отмена настройки","Настройка из кэша"],"src/tree":["Цель сборки: {0}","Целевой файл makefile, выбранный для сборки.","{0} (возникла проблема при отрисовке этого элемента)","Целевой объект запуска: {0}","Целевой объект запуска, выбранный для отладки и запуска в терминале.\n{0}","{0} (возникла проблема при отрисовке этого элемента)","Конфигурация: {0}","{0} (возникла проблема при отрисовке этого элемента)","{0}","{0} (возникла проблема при отрисовке этого элемента)","{0}","{0} (возникла проблема при отрисовке этого элемента)","{0}","{0} (возникла проблема при отрисовке этого элемента)","Удалить"],"src/util":["Завершение процесса PID=${0}..."]}